avpnrnpoytwouygev/__init__.py
avpnrnpoytwouygev/main.py
avpnrnpoytwouygev/version.py
avpnrnpoytwouygev-9.1.1.dist-info/METADATA
avpnrnpoytwouygev-9.1.1.dist-info/WHEEL
avpnrnpoytwouygev-9.1.1.dist-info/top_level.txt
avpnrnpoytwouygev-9.1.1.dist-info/RECORD
