Metadata-Version: 2.1
Name: avpnrnpoytwouygev
Version: 9.1.1
Summary: A random placeholder package for CI testing
Author: Francisco Castillo
Author-email: fjcastillocarrasco@gmail.com
Classifier: Development Status :: 1 - Planning
Classifier: Intended Audience :: Developers
Classifier: Programming Language :: Python :: 3.10
Classifier: Programming Language :: Python :: 3.11
Requires-Python: >=3.6
Requires-Dist: numpy >=1.24.0
